{
	"Opmode": [
        {"b": "OpArgR", "c": "OpArgN"},
        {"b": "OpArgK", "c": "OpArgN"},
        {"b": "OpArgU", "c": "OpArgU"},
        {"b": "OpArgR", "c": "OpArgN"},
        {"b": "OpArgU", "c": "OpArgN"},
        {"b": "OpArgK", "c": "OpArgN"},
        {"b": "OpArgR", "c": "OpArgK"},
        {"b": "OpArgK", "c": "OpArgN"},
        {"b": "OpArgU", "c": "OpArgN"},
        {"b": "OpArgK", "c": "OpArgK"},
        {"b": "OpArgU", "c": "OpArgU"},
        {"b": "OpArgR", "c": "OpArgK"},
        {"b": "OpArgK", "c": "OpArgK"},
        {"b": "OpArgK", "c": "OpArgK"},
        {"b": "OpArgK", "c": "OpArgK"},
        {"b": "OpArgK", "c": "OpArgK"},
        {"b": "OpArgK", "c": "OpArgK"},
        {"b": "OpArgK", "c": "OpArgK"},
        {"b": "OpArgR", "c": "OpArgN"},
        {"b": "OpArgR", "c": "OpArgN"},
        {"b": "OpArgR", "c": "OpArgN"},
        {"b": "OpArgR", "c": "OpArgR"},
        {"b": "OpArgR", "c": "OpArgN"},
        {"b": "OpArgK", "c": "OpArgK"},
        {"b": "OpArgK", "c": "OpArgK"},
        {"b": "OpArgK", "c": "OpArgK"},
        {"b": "OpArgR", "c": "OpArgU"},
        {"b": "OpArgR", "c": "OpArgU"},
        {"b": "OpArgU", "c": "OpArgU"},
        {"b": "OpArgU", "c": "OpArgU"},
        {"b": "OpArgU", "c": "OpArgN"},
        {"b": "OpArgR", "c": "OpArgN"},
        {"b": "OpArgR", "c": "OpArgN"},
        {"b": "OpArgN", "c": "OpArgU"},
        {"b": "OpArgU", "c": "OpArgU"},
        {"b": "OpArgN", "c": "OpArgN"},
        {"b": "OpArgU", "c": "OpArgN"},
        {"b": "OpArgU", "c": "OpArgN"}
    ],

    "Opcode": [ 
        "ABC",	"ABx",	"ABC",	"ABC",
        "ABC",	"ABx",	"ABC",	"ABx",
        "ABC",	"ABC",	"ABC",	"ABC",
        "ABC",	"ABC",	"ABC",	"ABC",
        "ABC",	"ABC",	"ABC",	"ABC",
        "ABC",	"ABC",	"AsBx",	"ABC",
        "ABC",	"ABC",	"ABC",	"ABC",
        "ABC",	"ABC",	"ABC",	"AsBx",
        "AsBx",	"ABC",	"ABC",	"ABC",
        "ABx",	"ABC"
    ],

    "Opnames": [
        "MOVE", "LOADK", "LOADBOOL", "LOADNIL",
        "GETUPVAL", "GETGLOBAL", "GETTABLE",
        "SETGLOBAL", "SETUPVAL", "SETTABLE",
        "NEWTABLE", "SELF",
        "ADD", "SUB", "MUL", "DIV",
        "MOD", "POW", "UNM", "NOT",
        "LEN", "CONCAT", "JMP",
        "EQ", "LT", "LE", "TEST",
        "TESTSET", "CALL", "TAILCALL",
        "RETURN", "FORLOOP", "FORPREP",
        "TFORLOOP", "SETLIST", "CLOSE",
        "CLOSURE", "VARARG"
    ]
}